Users/mikaelene/.eneel/example_connections.yml
eneel/__init__.py
eneel/config.py
eneel/load_runner.py
eneel/logger.py
eneel/main.py
eneel/printer.py
eneel/utils.py
eneel/adapters/__init__.py
eneel/adapters/oracle.py
eneel/adapters/postgres.py
eneel/adapters/sqlserver.py
eneel-0.1.4.dist-info/LICENSE
eneel-0.1.4.dist-info/METADATA
eneel-0.1.4.dist-info/WHEEL
eneel-0.1.4.dist-info/entry_points.txt
eneel-0.1.4.dist-info/top_level.txt
eneel-0.1.4.dist-info/RECORD
