Metadata-Version: 2.1
Name: eneel
Version: 0.1.4
Summary: A package for fast loading av relational data
Home-page: https://github.com/mikaelene/eneel
Author: Mikael Ene
Author-email: mikael.ene@gmail.com
License: UNKNOWN
Platform: UNKNOWN
Requires-Dist: pyodbc (>=4.0.27)
Requires-Dist: psycopg2 (>=2.7.7)
Requires-Dist: cx-Oracle (>=7.0.0)
Requires-Dist: PyYAML (>=3.11)
Requires-Dist: colorama (>=0.3.9)
